{
  "basics": {
    "name": "Martin Beaumont",
    "label": "Web Developer",
    "email": "hello@martinbeaumont.dev",
    "website": "https://martinbeaumont.dev/",
    "profiles": [
      {
        "network": "GitHub",
        "url": "https://github.com/martinbmnt",
        "username": "martinbmnt"
      },
      {
        "network": "Twitter",
        "url": "https://twitter.com/@martinbmnt",
        "username": "@martinbmnt"
      }
    ],
    "headline": "Building decentralized internet for everyone",
    "yearsOfExperience": 4,
    "username": "martinbmnt",
    "location": {
      "city": "Laval",
      "countryCode": "FR",
      "region": "France"
    }
  },
  "skills": [
    {
      "keywords": [
        "Symfony 4 / 5 / 6",
        "PHP 7 / 8",
        "MySQL / MariaDB"
      ],
      "level": "Advanced",
      "name": "Backend",
      "yearsOfExperience": 5
    },
    {
      "keywords": [
        "HTML / Semantic / Accessibility",
        "CSS / SCSS / BEM / Tailwind CSS",
        "Javascript / Typescript"
      ],
      "level": "Advanced",
      "name": "Frontend",
      "yearsOfExperience": 5
    }
  ],
  "meta": {
    "theme": "flat",
    "canonical": "https://raw.githubusercontent.com/martinbmnt/resume/main/resume.json",
    "lastModified": "2022-03-05T18:43:00"
  },
  "$schema": "https://raw.githubusercontent.com/jsonresume/resume-schema/v1.0.0/schema.json"
}